MANIFEST.in
README.rst
setup.py
test/bar.txt
test/example.yaml
test/foo.txt
test/test_cmdline.py
test/test_functionality.py
test/test_readers.py
toolaudit/__init__.py
toolaudit/application.py
toolaudit/kitlist.py
toolaudit/readers.py
toolaudit/testers.py
toolaudit.egg-info/PKG-INFO
toolaudit.egg-info/SOURCES.txt
toolaudit.egg-info/dependency_links.txt
toolaudit.egg-info/entry_points.txt
toolaudit.egg-info/not-zip-safe
toolaudit.egg-info/pbr.json
toolaudit.egg-info/requires.txt
toolaudit.egg-info/top_level.txt