Metadata-Version: 1.0
Name: toolaudit
Version: 0.0.4
Summary: Report on the tools used in your software pipeline.
Home-page: https://github.com/jstutters/toolaudit
Author: Jon Stutters
Author-email: j.stutters@ucl.ac.uk
License: MIT
Platform: UNKNOWN
Classifier: Programming Language :: Python
Classifier: Development Status :: 3 - Alpha
Classifier: Natural Language :: English
Classifier: Environment :: Console
Classifier: Intended Audience :: System Administrators
Classifier: License :: OSI Approved :: MIT License
Classifier: Operating System :: POSIX
Classifier: Topic :: System :: Systems Administration
